smokestack/VERSION
smokestack/__init__.py
smokestack/aws.py
smokestack/change_set.py
smokestack/cli.py
smokestack/operator.py
smokestack/py.typed
smokestack/register.py
smokestack/stack.py
smokestack/stack_set.py
smokestack/enums/__init__.py
smokestack/enums/py.typed
smokestack/enums/stack_status.py
smokestack/exceptions/__init__.py
smokestack/exceptions/change_set_creation.py
smokestack/exceptions/change_set_execution.py
smokestack/exceptions/configuration_error.py
smokestack/exceptions/py.typed
smokestack/exceptions/smokestack.py
smokestack/exceptions/stack.py
smokestack/tasks/__init__.py
smokestack/tasks/operate.py
smokestack/types/__init__.py
smokestack/types/capability.py
smokestack/types/change_type.py
smokestack/types/operation.py
smokestack/types/operation_result.py
smokestack/types/py.typed
smokestack/types/stack_parameter.py
smokestack-1.0.0a16.dist-info/LICENSE
smokestack-1.0.0a16.dist-info/METADATA
smokestack-1.0.0a16.dist-info/WHEEL
smokestack-1.0.0a16.dist-info/top_level.txt
smokestack-1.0.0a16.dist-info/RECORD
