Metadata-Version: 2.1
Name: smokestack
Version: 1.0.0a16
Summary: CloudFormation stacks, beautifully
Home-page: https://github.com/cariad/smokestack
Author: Cariad Eccleston
Author-email: cariad@cariad.earth
License: MIT
Platform: UNKNOWN
Classifier: Development Status :: 3 - Alpha
Classifier: License :: OSI Approved :: MIT License
Classifier: Natural Language :: English
Classifier: Programming Language :: Python :: 3 :: Only
Classifier: Programming Language :: Python :: 3.10
Classifier: Programming Language :: Python :: 3.8
Classifier: Programming Language :: Python :: 3.9
Classifier: Typing :: Typed
Requires-Python: >=3.8
License-File: LICENSE
Requires-Dist: ansiscape (~=1.0)
Requires-Dist: boto3 (~=1.20)
Requires-Dist: cfp (~=1.1)
Requires-Dist: cline (~=1.2)
Requires-Dist: pyyaml (~=6.0)
Requires-Dist: stackdiff (~=1.1)
Requires-Dist: stackwhy (~=1.0.1)
